Metadata-Version: 2.2
Name: sop_deutils
Version: 1.2.6
Summary: A utils package for Yes4All SOP
Author-email: liuliukiki aka clong aka ifyouknowyouknow101 <longnc@yes4all.com>
Project-URL: Author_Github, https://github.com/dribblewithclong
Classifier: Programming Language :: Python :: 3
Classifier: License :: OSI Approved :: MIT License
Classifier: Operating System :: OS Independent
Requires-Python: >=3.7
License-File: LICENSE
Requires-Dist: openpyxl==3.1.2
Requires-Dist: pytz==2023.3
Requires-Dist: pandas==2.0.3
Requires-Dist: python-telegram-bot==20.5
Requires-Dist: SQLAlchemy==1.4.49
Requires-Dist: lxml==4.9.3
Requires-Dist: gspread==5.11.1
Requires-Dist: psycopg2-binary==2.9.7
Requires-Dist: minio==7.1.16
Requires-Dist: pyarrow==11.0.0
Requires-Dist: requests==2.30.0
Requires-Dist: aiofiles==23.2.1
Requires-Dist: fastparquet==2023.8.0
Requires-Dist: mysql-connector-python==8.1.0
Requires-Dist: SQLAlchemy==1.4.49
Requires-Dist: httplib2==0.22.0
Requires-Dist: python-dateutil==2.9.0.post0
Requires-Dist: cryptography==42.0.7
Requires-Dist: PyYAML==6.0.1
Requires-Dist: gspread-dataframe==3.3.1
Requires-Dist: google-auth==2.22.0
Requires-Dist: google-api-python-client==1.6.7
Requires-Dist: trino==0.324.0
